skybaks/cup_manager/__init__.py
skybaks/cup_manager/active.py
skybaks/cup_manager/app.py
skybaks/cup_manager/app_types.py
skybaks/cup_manager/payouts.py
skybaks/cup_manager/results.py
skybaks/cup_manager/setup.py
skybaks/cup_manager/migrations/000_add_cup_host.py
skybaks/cup_manager/migrations/001_clean_table_names.py
skybaks/cup_manager/migrations/002_add_map_medals.py
skybaks/cup_manager/migrations/003_add_scoremode.py
skybaks/cup_manager/models/__init__.py
skybaks/cup_manager/models/cup_model.py
skybaks/cup_manager/models/match_info.py
skybaks/cup_manager/models/player_score.py
skybaks/cup_manager/models/team_score.py
skybaks/cup_manager/score_mode/__init__.py
skybaks/cup_manager/score_mode/mode_logic.py
skybaks/cup_manager/score_mode/mode_logic_singular.py
skybaks/cup_manager/score_mode/score_base.py
skybaks/cup_manager/score_mode/score_fallback.py
skybaks/cup_manager/score_mode/score_laps.py
skybaks/cup_manager/score_mode/score_mixed.py
skybaks/cup_manager/score_mode/score_rounds.py
skybaks/cup_manager/score_mode/score_timeattack.py
skybaks/cup_manager/utils/__init__.py
skybaks/cup_manager/utils/country_codes.py
skybaks/cup_manager/utils/markdown.py
skybaks/cup_manager/utils/placements.py
skybaks/cup_manager/views/__init__.py
skybaks/cup_manager/views/cup_view.py
skybaks/cup_manager/views/match_history_view.py
skybaks/cup_manager/views/options_view.py
skybaks/cup_manager/views/results_view.py
skybaks/cup_manager/views/single_instance_view.py
skybaks/cup_manager/views/textbox_view.py
skybaks/cup_manager/templates/options.xml
skybaks/cup_manager/templates/textbox.Script.txt
skybaks/cup_manager/templates/textbox.xml
pyplanet_cup_manager-4.0.0.dist-info/METADATA
pyplanet_cup_manager-4.0.0.dist-info/WHEEL
pyplanet_cup_manager-4.0.0.dist-info/licenses/license
pyplanet_cup_manager-4.0.0.dist-info/RECORD
