Metadata-Version: 2.1
Name: pyplanet-cup_manager
Version: 4.0.0
Summary: A Pyplanet server controller plugin for hosting competitions
Project-URL: Homepage, https://github.com/skybaks/pyplanet-cup_manager
Project-URL: Bug Tracker, https://github.com/skybaks/pyplanet-cup_manager/issues
Author-email: skybaks <tmflame@gmail.com>
License-File: license
Classifier: License :: OSI Approved :: GNU General Public License v3 (GPLv3)
Classifier: Operating System :: OS Independent
Classifier: Programming Language :: Python :: 3
Classifier: Programming Language :: Python :: 3 :: Only
Classifier: Topic :: Games/Entertainment
Requires-Python: >=3.7
